README.md
setup.py
FlaskCurrency.egg-info/PKG-INFO
FlaskCurrency.egg-info/SOURCES.txt
FlaskCurrency.egg-info/dependency_links.txt
FlaskCurrency.egg-info/top_level.txt
flask_currency/__init__.py
flask_currency/core.py
flask_currency/model.py
flask_currency/money.py