Metadata-Version: 2.1
Name: FlaskCurrency
Version: 1.0
Summary: Currency handling extension for Flask and SQLAlchemy
Home-page: https://github.com/gerelorant/Flask-Currency
Author: Gere Lóránt
Author-email: gerelorant@gmail.com
License: MIT
Platform: UNKNOWN
